{
  "id": "d3024c78-3686-487e-bba8-d736c5bef804",
  "prevId": "00000000-0000-0000-0000-000000000000",
  "version": "7",
  "dialect": "postgresql",
  "tables": {
    "public.albums": {
      "name": "albums",
      "schema": "",
      "columns": {
        "id": {
          "name": "id",
          "type": "uuid",
          "primaryKey": true,
          "notNull": true,
          "default": "gen_random_uuid()"
        },
        "spotify_id": {
          "name": "spotify_id",
          "type": "text",
          "primaryKey": false,
          "notNull": true
        },
        "title": {
          "name": "title",
          "type": "text",
          "primaryKey": false,
          "notNull": true
        },
        "artist": {
          "name": "artist",
          "type": "text",
          "primaryKey": false,
          "notNull": true
        },
        "year": {
          "name": "year",
          "type": "integer",
          "primaryKey": false,
          "notNull": true
        },
        "cover_url": {
          "name": "cover_url",
          "type": "text",
          "primaryKey": false,
          "notNull": true
        },
        "genre": {
          "name": "genre",
          "type": "text",
          "primaryKey": false,
          "notNull": false
        }
      },
      "indexes": {},
      "foreignKeys": {},
      "compositePrimaryKeys": {},
      "uniqueConstraints": {
        "albums_spotify_id_unique": {
          "name": "albums_spotify_id_unique",
          "nullsNotDistinct": false,
          "columns": [
            "spotify_id"
          ]
        }
      },
      "policies": {},
      "checkConstraints": {},
      "isRLSEnabled": false
    },
    "public.catalog_entries": {
      "name": "catalog_entries",
      "schema": "",
      "columns": {
        "id": {
          "name": "id",
          "type": "uuid",
          "primaryKey": true,
          "notNull": true,
          "default": "gen_random_uuid()"
        },
        "user_id": {
          "name": "user_id",
          "type": "uuid",
          "primaryKey": false,
          "notNull": true
        },
        "album_id": {
          "name": "album_id",
          "type": "uuid",
          "primaryKey": false,
          "notNull": true
        },
        "added_at": {
          "name": "added_at",
          "type": "timestamp",
          "primaryKey": false,
          "notNull": true,
          "default": "now()"
        }
      },
      "indexes": {},
      "foreignKeys": {
        "catalog_entries_user_id_users_id_fk": {
          "name": "catalog_entries_user_id_users_id_fk",
          "tableFrom": "catalog_entries",
          "tableTo": "users",
          "columnsFrom": [
            "user_id"
          ],
          "columnsTo": [
            "id"
          ],
          "onDelete": "cascade",
          "onUpdate": "no action"
        },
        "catalog_entries_album_id_albums_id_fk": {
          "name": "catalog_entries_album_id_albums_id_fk",
          "tableFrom": "catalog_entries",
          "tableTo": "albums",
          "columnsFrom": [
            "album_id"
          ],
          "columnsTo": [
            "id"
          ],
          "onDelete": "cascade",
          "onUpdate": "no action"
        }
      },
      "compositePrimaryKeys": {},
      "uniqueConstraints": {
        "catalog_entries_user_id_album_id_unique": {
          "name": "catalog_entries_user_id_album_id_unique",
          "nullsNotDistinct": false,
          "columns": [
            "user_id",
            "album_id"
          ]
        }
      },
      "policies": {},
      "checkConstraints": {},
      "isRLSEnabled": false
    },
    "public.favorite_tracks": {
      "name": "favorite_tracks",
      "schema": "",
      "columns": {
        "id": {
          "name": "id",
          "type": "uuid",
          "primaryKey": true,
          "notNull": true,
          "default": "gen_random_uuid()"
        },
        "user_id": {
          "name": "user_id",
          "type": "uuid",
          "primaryKey": false,
          "notNull": true
        },
        "album_id": {
          "name": "album_id",
          "type": "uuid",
          "primaryKey": false,
          "notNull": true
        },
        "review_id": {
          "name": "review_id",
          "type": "uuid",
          "primaryKey": false,
          "notNull": true
        },
        "track_id": {
          "name": "track_id",
          "type": "text",
          "primaryKey": false,
          "notNull": true
        },
        "track_name": {
          "name": "track_name",
          "type": "text",
          "primaryKey": false,
          "notNull": true
        }
      },
      "indexes": {},
      "foreignKeys": {
        "favorite_tracks_user_id_users_id_fk": {
          "name": "favorite_tracks_user_id_users_id_fk",
          "tableFrom": "favorite_tracks",
          "tableTo": "users",
          "columnsFrom": [
            "user_id"
          ],
          "columnsTo": [
            "id"
          ],
          "onDelete": "cascade",
          "onUpdate": "no action"
        },
        "favorite_tracks_album_id_albums_id_fk": {
          "name": "favorite_tracks_album_id_albums_id_fk",
          "tableFrom": "favorite_tracks",
          "tableTo": "albums",
          "columnsFrom": [
            "album_id"
          ],
          "columnsTo": [
            "id"
          ],
          "onDelete": "cascade",
          "onUpdate": "no action"
        },
        "favorite_tracks_review_id_reviews_id_fk": {
          "name": "favorite_tracks_review_id_reviews_id_fk",
          "tableFrom": "favorite_tracks",
          "tableTo": "reviews",
          "columnsFrom": [
            "review_id"
          ],
          "columnsTo": [
            "id"
          ],
          "onDelete": "cascade",
          "onUpdate": "no action"
        }
      },
      "compositePrimaryKeys": {},
      "uniqueConstraints": {
        "favorite_tracks_user_id_album_id_track_id_unique": {
          "name": "favorite_tracks_user_id_album_id_track_id_unique",
          "nullsNotDistinct": false,
          "columns": [
            "user_id",
            "album_id",
            "track_id"
          ]
        }
      },
      "policies": {},
      "checkConstraints": {},
      "isRLSEnabled": false
    },
    "public.users": {
      "name": "users",
      "schema": "",
      "columns": {
        "id": {
          "name": "id",
          "type": "uuid",
          "primaryKey": true,
          "notNull": true,
          "default": "gen_random_uuid()"
        },
        "name": {
          "name": "name",
          "type": "text",
          "primaryKey": false,
          "notNull": true
        },
        "email": {
          "name": "email",
          "type": "text",
          "primaryKey": false,
          "notNull": true
        },
        "password": {
          "name": "password",
          "type": "text",
          "primaryKey": false,
          "notNull": true
        },
        "role": {
          "name": "role",
          "type": "role",
          "typeSchema": "public",
          "primaryKey": false,
          "notNull": true,
          "default": "'USER'"
        },
        "created_at": {
          "name": "created_at",
          "type": "timestamp",
          "primaryKey": false,
          "notNull": true,
          "default": "now()"
        },
        "updated_at": {
          "name": "updated_at",
          "type": "timestamp",
          "primaryKey": false,
          "notNull": true,
          "default": "now()"
        }
      },
      "indexes": {},
      "foreignKeys": {},
      "compositePrimaryKeys": {},
      "uniqueConstraints": {
        "users_email_unique": {
          "name": "users_email_unique",
          "nullsNotDistinct": false,
          "columns": [
            "email"
          ]
        }
      },
      "policies": {},
      "checkConstraints": {},
      "isRLSEnabled": false
    },
    "public.reviews": {
      "name": "reviews",
      "schema": "",
      "columns": {
        "id": {
          "name": "id",
          "type": "uuid",
          "primaryKey": true,
          "notNull": true,
          "default": "gen_random_uuid()"
        },
        "user_id": {
          "name": "user_id",
          "type": "uuid",
          "primaryKey": false,
          "notNull": true
        },
        "album_id": {
          "name": "album_id",
          "type": "uuid",
          "primaryKey": false,
          "notNull": true
        },
        "catalog_entry_id": {
          "name": "catalog_entry_id",
          "type": "uuid",
          "primaryKey": false,
          "notNull": true
        },
        "review_text": {
          "name": "review_text",
          "type": "text",
          "primaryKey": false,
          "notNull": false
        },
        "month_listened": {
          "name": "month_listened",
          "type": "timestamp",
          "primaryKey": false,
          "notNull": true
        },
        "recommended_by": {
          "name": "recommended_by",
          "type": "text",
          "primaryKey": false,
          "notNull": false
        },
        "created_at": {
          "name": "created_at",
          "type": "timestamp",
          "primaryKey": false,
          "notNull": true,
          "default": "now()"
        },
        "updated_at": {
          "name": "updated_at",
          "type": "timestamp",
          "primaryKey": false,
          "notNull": true,
          "default": "now()"
        }
      },
      "indexes": {},
      "foreignKeys": {
        "reviews_user_id_users_id_fk": {
          "name": "reviews_user_id_users_id_fk",
          "tableFrom": "reviews",
          "tableTo": "users",
          "columnsFrom": [
            "user_id"
          ],
          "columnsTo": [
            "id"
          ],
          "onDelete": "cascade",
          "onUpdate": "no action"
        },
        "reviews_album_id_albums_id_fk": {
          "name": "reviews_album_id_albums_id_fk",
          "tableFrom": "reviews",
          "tableTo": "albums",
          "columnsFrom": [
            "album_id"
          ],
          "columnsTo": [
            "id"
          ],
          "onDelete": "cascade",
          "onUpdate": "no action"
        },
        "reviews_catalog_entry_id_catalog_entries_id_fk": {
          "name": "reviews_catalog_entry_id_catalog_entries_id_fk",
          "tableFrom": "reviews",
          "tableTo": "catalog_entries",
          "columnsFrom": [
            "catalog_entry_id"
          ],
          "columnsTo": [
            "id"
          ],
          "onDelete": "cascade",
          "onUpdate": "no action"
        }
      },
      "compositePrimaryKeys": {},
      "uniqueConstraints": {
        "reviews_catalog_entry_id_unique": {
          "name": "reviews_catalog_entry_id_unique",
          "nullsNotDistinct": false,
          "columns": [
            "catalog_entry_id"
          ]
        }
      },
      "policies": {},
      "checkConstraints": {},
      "isRLSEnabled": false
    },
    "public.lists": {
      "name": "lists",
      "schema": "",
      "columns": {
        "id": {
          "name": "id",
          "type": "uuid",
          "primaryKey": true,
          "notNull": true,
          "default": "gen_random_uuid()"
        },
        "user_id": {
          "name": "user_id",
          "type": "uuid",
          "primaryKey": false,
          "notNull": true
        },
        "name": {
          "name": "name",
          "type": "text",
          "primaryKey": false,
          "notNull": true
        },
        "created_at": {
          "name": "created_at",
          "type": "timestamp",
          "primaryKey": false,
          "notNull": true,
          "default": "now()"
        },
        "updated_at": {
          "name": "updated_at",
          "type": "timestamp",
          "primaryKey": false,
          "notNull": true,
          "default": "now()"
        }
      },
      "indexes": {},
      "foreignKeys": {
        "lists_user_id_users_id_fk": {
          "name": "lists_user_id_users_id_fk",
          "tableFrom": "lists",
          "tableTo": "users",
          "columnsFrom": [
            "user_id"
          ],
          "columnsTo": [
            "id"
          ],
          "onDelete": "cascade",
          "onUpdate": "no action"
        }
      },
      "compositePrimaryKeys": {},
      "uniqueConstraints": {},
      "policies": {},
      "checkConstraints": {},
      "isRLSEnabled": false
    },
    "public.list_albums": {
      "name": "list_albums",
      "schema": "",
      "columns": {
        "id": {
          "name": "id",
          "type": "uuid",
          "primaryKey": true,
          "notNull": true,
          "default": "gen_random_uuid()"
        },
        "list_id": {
          "name": "list_id",
          "type": "uuid",
          "primaryKey": false,
          "notNull": true
        },
        "album_id": {
          "name": "album_id",
          "type": "uuid",
          "primaryKey": false,
          "notNull": true
        },
        "added_at": {
          "name": "added_at",
          "type": "timestamp",
          "primaryKey": false,
          "notNull": true,
          "default": "now()"
        }
      },
      "indexes": {},
      "foreignKeys": {
        "list_albums_list_id_lists_id_fk": {
          "name": "list_albums_list_id_lists_id_fk",
          "tableFrom": "list_albums",
          "tableTo": "lists",
          "columnsFrom": [
            "list_id"
          ],
          "columnsTo": [
            "id"
          ],
          "onDelete": "cascade",
          "onUpdate": "no action"
        },
        "list_albums_album_id_albums_id_fk": {
          "name": "list_albums_album_id_albums_id_fk",
          "tableFrom": "list_albums",
          "tableTo": "albums",
          "columnsFrom": [
            "album_id"
          ],
          "columnsTo": [
            "id"
          ],
          "onDelete": "cascade",
          "onUpdate": "no action"
        }
      },
      "compositePrimaryKeys": {},
      "uniqueConstraints": {
        "list_albums_list_id_album_id_unique": {
          "name": "list_albums_list_id_album_id_unique",
          "nullsNotDistinct": false,
          "columns": [
            "list_id",
            "album_id"
          ]
        }
      },
      "policies": {},
      "checkConstraints": {},
      "isRLSEnabled": false
    }
  },
  "enums": {
    "public.role": {
      "name": "role",
      "schema": "public",
      "values": [
        "USER",
        "ADMIN"
      ]
    }
  },
  "schemas": {},
  "sequences": {},
  "roles": {},
  "policies": {},
  "views": {},
  "_meta": {
    "columns": {},
    "schemas": {},
    "tables": {}
  }
}